{
  "experiment": "EXP-05",
  "test_type": "Compression/Expansion Losslessness",
  "start_time": "2026-01-08T16:32:48.454093+00:00",
  "end_time": "2026-01-08T16:32:48.459108+00:00",
  "total_duration_seconds": 0.005,
  "bitchains_tested": 20,
  "aggregate_metrics": {
    "avg_compression_ratio": 0.479,
    "avg_luminosity_decay_ratio": 0.405,
    "avg_coordinate_accuracy": 0.0,
    "percent_provenance_intact": 0.0,
    "percent_narrative_preserved": 0.0,
    "percent_expandable": 0.0
  },
  "compression_quality": {
    "is_lossless": false,
    "major_findings": [
      "[WARN] Provenance loss detected (100.0% affected)",
      "[WARN] Narrative degradation observed (100.0% affected)",
      "[FAIL] FractalStat coordinate recovery insufficient (0.0%)",
      "[WARN] Compression ratio modest (0.48x)",
      "[WARN] Luminosity decay significant (40.5% loss)"
    ]
  },
  "sample_paths": [
    {
      "original_realm": "system",
      "original_address": "bba5f61e108e1a65...",
      "stages_count": 5,
      "compression_ratio": 0.4224137931034483,
      "luminosity_decay": 29.1322521531512,
      "coordinate_accuracy": 0.0,
      "provenance_intact": false,
      "narrative_preserved": false,
      "can_expand": false,
      "final_stage": "mist"
    },
    {
      "original_realm": "faculty",
      "original_address": "ec03b72b47fba65f...",
      "stages_count": 5,
      "compression_ratio": 0.5257301808066759,
      "luminosity_decay": 3.5524073838260417,
      "coordinate_accuracy": 0.0,
      "provenance_intact": false,
      "narrative_preserved": false,
      "can_expand": false,
      "final_stage": "mist"
    },
    {
      "original_realm": "data",
      "original_address": "979ad40eba926f27...",
      "stages_count": 5,
      "compression_ratio": 0.42327150084317033,
      "luminosity_decay": 8.468638552722506,
      "coordinate_accuracy": 0.0,
      "provenance_intact": false,
      "narrative_preserved": false,
      "can_expand": false,
      "final_stage": "mist"
    },
    {
      "original_realm": "narrative",
      "original_address": "f8c7f2fcff0b6e2e...",
      "stages_count": 5,
      "compression_ratio": 0.5255172413793103,
      "luminosity_decay": 30.9415417212846,
      "coordinate_accuracy": 0.0,
      "provenance_intact": false,
      "narrative_preserved": false,
      "can_expand": false,
      "final_stage": "mist"
    },
    {
      "original_realm": "system",
      "original_address": "29d648b660e4f4eb...",
      "stages_count": 5,
      "compression_ratio": 0.4694835680751174,
      "luminosity_decay": 21.231438268521597,
      "coordinate_accuracy": 0.0,
      "provenance_intact": false,
      "narrative_preserved": false,
      "can_expand": false,
      "final_stage": "mist"
    }
  ],
  "all_valid": false
}